napari_ome_zarr_navigator/__init__.py
napari_ome_zarr_navigator/_sample_data.py
napari_ome_zarr_navigator/_version.py
napari_ome_zarr_navigator/_widget.py
napari_ome_zarr_navigator/img_browser.py
napari_ome_zarr_navigator/napari.yaml
napari_ome_zarr_navigator/roi_loader.py
napari_ome_zarr_navigator/roi_loading_utils.py
napari_ome_zarr_navigator/roi_run_script.py
napari_ome_zarr_navigator/run_img_browser.py
napari_ome_zarr_navigator/util.py
napari_ome_zarr_navigator/_tests/__init__.py
napari_ome_zarr_navigator/_tests/conftest.py
napari_ome_zarr_navigator/_tests/no_run_test_sample_data.py
napari_ome_zarr_navigator/_tests/test_img_browser.py
napari_ome_zarr_navigator/_tests/test_roi_loader.py
napari_ome_zarr_navigator/generate_test_data/__init__.py
napari_ome_zarr_navigator/generate_test_data/generate_condition_table.ipynb
napari_ome_zarr_navigator/generate_test_data/workflow-export-navigator_test_dataset_creation-1703255291595.json
napari_ome_zarr_navigator/icons/eye-off.svg
napari_ome_zarr_navigator/icons/eye.svg
napari_ome_zarr_navigator-0.2.4.dist-info/licenses/LICENSE
napari_ome_zarr_navigator-0.2.4.dist-info/METADATA
napari_ome_zarr_navigator-0.2.4.dist-info/WHEEL
napari_ome_zarr_navigator-0.2.4.dist-info/entry_points.txt
napari_ome_zarr_navigator-0.2.4.dist-info/top_level.txt
napari_ome_zarr_navigator-0.2.4.dist-info/RECORD
