Metadata-Version: 2.4
Name: napari-ome-zarr-navigator
Version: 0.2.4
Summary: A plugin to browse OME-Zarr plates by conditions and load images, labels and features from ROIs
Home-page: https://github.com/fractal-analytics-platform/napari-ome-zarr-navigator
Author: Fabio Steffen and Joel Luethi
Author-email: fabio.steffen@uzh.ch
License: BSD-3-Clause
Project-URL: Bug Tracker, https://github.com/fractal-analytics-platform/napari-ome-zarr-navigator/issues
Project-URL: Documentation, https://github.com/fractal-analytics-platform/napari-ome-zarr-navigator#README.md
Project-URL: Source Code, https://github.com/fractal-analytics-platform/napari-ome-zarr-navigator
Project-URL: User Support, https://github.com/fractal-analytics-platform/napari-ome-zarr-navigator/issues
Classifier: Development Status :: 2 - Pre-Alpha
Classifier: Framework :: napari
Classifier: Intended Audience :: Developers
Classifier: License :: OSI Approved :: BSD License
Classifier: Operating System :: OS Independent
Classifier: Programming Language :: Python
Classifier: Programming Language :: Python :: 3
Classifier: Programming Language :: Python :: 3 :: Only
Classifier: Programming Language :: Python :: 3.11
Classifier: Programming Language :: Python :: 3.12
Classifier: Topic :: Scientific/Engineering :: Image Processing
Requires-Python: >=3.11
License-File: LICENSE
Requires-Dist: numpy
Requires-Dist: magicgui
Requires-Dist: qtpy
Requires-Dist: scikit-image
Requires-Dist: napari-ome-zarr
Requires-Dist: ome-zarr
Requires-Dist: wget
Requires-Dist: ngio>=0.4.0
Requires-Dist: numcodecs!=0.14.0,!=0.14.1,!=0.16
Provides-Extra: testing
Requires-Dist: tox; extra == "testing"
Requires-Dist: pytest; extra == "testing"
Requires-Dist: pytest-cov; extra == "testing"
Requires-Dist: pytest-qt; extra == "testing"
Requires-Dist: napari; extra == "testing"
Requires-Dist: pyqt5; extra == "testing"
Dynamic: license-file
